pitlakq/__init__.py
pitlakq/__main__.py
pitlakq/commontools/__init__.py
pitlakq/commontools/tools.py
pitlakq/commontools/datastructures/__init__.py
pitlakq/commontools/datastructures/dicts.py
pitlakq/commontools/dbftools/__init__.py
pitlakq/commontools/dbftools/flatdbf/__init__.py
pitlakq/commontools/dbftools/flatdbf/flatdbf.py
pitlakq/commontools/dbftools/pcg/__init__.py
pitlakq/commontools/dbftools/pcg/pcgdatabase.py
pitlakq/commontools/dirs/__init__.py
pitlakq/commontools/dirs/splitall.py
pitlakq/commontools/filereader/__init__.py
pitlakq/commontools/filereader/fobj.py
pitlakq/commontools/filereader/read_columns_txt.py
pitlakq/commontools/input/__init__.py
pitlakq/commontools/input/bathhelper.py
pitlakq/commontools/input/recursiveupdate.py
pitlakq/commontools/input/resources.py
pitlakq/commontools/input/xlsx_reader.py
pitlakq/commontools/input/yamlinput.py
pitlakq/commontools/output/__init__.py
pitlakq/commontools/output/ncoutput.py
pitlakq/commontools/timing/__init__.py
pitlakq/commontools/timing/timetools.py
pitlakq/metamodel/__init__.py
pitlakq/metamodel/balance/__init__.py
pitlakq/metamodel/balance/balance.py
pitlakq/metamodel/balance/specie_balance.py
pitlakq/metamodel/configuration/__init__.py
pitlakq/metamodel/configuration/configuration.py
pitlakq/metamodel/configuration/getconfig.py
pitlakq/metamodel/configuration/initialize.py
pitlakq/metamodel/configuration/version.py
pitlakq/metamodel/running/__init__.py
pitlakq/metamodel/running/db.py
pitlakq/metamodel/running/gw_lake_exchange.py
pitlakq/metamodel/running/importhelper.py
pitlakq/metamodel/running/introspection.py
pitlakq/metamodel/running/pitlakq_scripter.py
pitlakq/metamodel/running/run_pitlakq.py
pitlakq/metamodel/running/runlab.py
pitlakq/numericalmodels/__init__.py
pitlakq/numericalmodels/existingmodels/__init__.py
pitlakq/numericalmodels/existingmodels/modflow/__init__.py
pitlakq/numericalmodels/existingmodels/modmst/__init__.py
pitlakq/numericalmodels/existingmodels/modmst/modmst.py
pitlakq-1.7.8.dist-info/METADATA
pitlakq-1.7.8.dist-info/WHEEL
pitlakq-1.7.8.dist-info/entry_points.txt
pitlakq-1.7.8.dist-info/RECORD
