Metadata-Version: 2.4
Name: PITLAKQ
Version: 1.7.8
Summary: The Pit Lake Hydrodynamic and Water Quality Model
Project-URL: Homepage, http://www.pitlakq.com
Project-URL: Documentation, https://github.com/pypa/sampleproject/issues
Author-email: Mike Müller <mmueller@hydrocomputing.com>
Classifier: Development Status :: 4 - Beta
Classifier: Environment :: Console
Classifier: Intended Audience :: Developers
Classifier: Intended Audience :: Science/Research
Classifier: License :: OSI Approved :: BSD License
Classifier: Operating System :: OS Independent
Classifier: Programming Language :: Python
Classifier: Programming Language :: Python :: 3.9
Classifier: Programming Language :: Python :: 3.10
Classifier: Programming Language :: Python :: 3.11
Classifier: Programming Language :: Python :: Implementation :: CPython
Classifier: Topic :: Scientific/Engineering :: Chemistry
Requires-Python: >=3.9
Requires-Dist: jupyterlab
Requires-Dist: libpitlakq
Requires-Dist: matplotlib
Requires-Dist: netcdf4
Requires-Dist: numpy
Requires-Dist: openpyxl
Requires-Dist: pandas
Requires-Dist: pyro4
Requires-Dist: pywin32; sys_platform == 'win32'
Requires-Dist: pyyaml
Requires-Dist: scipy
Requires-Dist: xlsxwriter
Requires-Dist: zodb
